repoprune/repoprune.py
prune_container_repo-0.0.4.dist-info/LICENSE
prune_container_repo-0.0.4.dist-info/METADATA
prune_container_repo-0.0.4.dist-info/WHEEL
prune_container_repo-0.0.4.dist-info/entry_points.txt
prune_container_repo-0.0.4.dist-info/top_level.txt
prune_container_repo-0.0.4.dist-info/RECORD
