Metadata-Version: 2.1
Name: prune-container-repo
Version: 0.0.4
License-File: LICENSE
Requires-Dist: requests
Requires-Dist: python-dateutil
Requires-Dist: tabulate
